topsis/__init__.py
topsis/topsis.py
topsis_sanchita_10155792-1.0.1.dist-info/METADATA
topsis_sanchita_10155792-1.0.1.dist-info/WHEEL
topsis_sanchita_10155792-1.0.1.dist-info/entry_points.txt
topsis_sanchita_10155792-1.0.1.dist-info/top_level.txt
topsis_sanchita_10155792-1.0.1.dist-info/RECORD
