Metadata-Version: 2.4
Name: topsis-sanchita-10155792
Version: 1.0.1
Summary: TOPSIS implementation as a Python package
Author: Sanchita Sharma
Requires-Dist: numpy
Requires-Dist: pandas
Dynamic: author
Dynamic: description-content-type
Dynamic: requires-dist
Dynamic: summary
